[
  {
    "id": "rosette_preset_1765011394179",
    "lane": "rosette",
    "name": "Safe Default",
    "params": {
      "feed_xy": 800,
      "stepdown": 1.0
    },
    "created_at": 1765011394.1790996
  },
  {
    "id": "rosette_preset_1765031860157",
    "lane": "rosette",
    "name": "Safe Default",
    "params": {
      "feed_xy": 800,
      "stepdown": 1.0
    },
    "created_at": 1765031860.1579769
  },
  {
    "id": "rosette_preset_1765038492426",
    "lane": "rosette",
    "name": "Safe Default",
    "params": {
      "feed_xy": 800,
      "stepdown": 1.0
    },
    "created_at": 1765038492.4267266
  },
  {
    "id": "rosette_preset_1765045028483",
    "lane": "rosette",
    "name": "Safe Default",
    "params": {
      "feed_xy": 800,
      "stepdown": 1.0
    },
    "created_at": 1765045028.4834263
  },
  {
    "id": "rosette_preset_1765045264773",
    "lane": "rosette",
    "name": "Safe Default",
    "params": {
      "feed_xy": 800,
      "stepdown": 1.0
    },
    "created_at": 1765045264.773194
  },
  {
    "id": "rosette_preset_1765046877899",
    "lane": "rosette",
    "name": "Safe Default",
    "params": {
      "feed_xy": 800,
      "stepdown": 1.0
    },
    "created_at": 1765046877.8993673
  },
  {
    "id": "rosette_preset_1765055360380",
    "lane": "rosette",
    "name": "Safe Default",
    "params": {
      "feed_xy": 800,
      "stepdown": 1.0
    },
    "created_at": 1765055360.3803265
  },
  {
    "id": "rosette_preset_1765073137123",
    "lane": "rosette",
    "name": "Safe Default",
    "params": {
      "feed_xy": 800,
      "stepdown": 1.0
    },
    "created_at": 1765073137.1235113
  },
  {
    "id": "rosette_preset_1767778145940",
    "lane": "rosette",
    "name": "Safe Default",
    "params": {
      "feed_xy": 800,
      "stepdown": 1.0
    },
    "created_at": 1767778145.9409091
  },
  {
    "id": "rosette_preset_1767778826768",
    "lane": "rosette",
    "name": "Safe Default",
    "params": {
      "feed_xy": 800,
      "stepdown": 1.0
    },
    "created_at": 1767778826.768571
  },
  {
    "id": "rosette_preset_1767780337442",
    "lane": "rosette",
    "name": "Safe Default",
    "params": {
      "feed_xy": 800,
      "stepdown": 1.0
    },
    "created_at": 1767780337.442842
  },
  {
    "id": "rosette_preset_1768007699224",
    "lane": "rosette",
    "name": "Safe Default",
    "params": {
      "feed_xy": 800,
      "stepdown": 1.0
    },
    "created_at": 1768007699.2245147
  },
  {
    "id": "rosette_preset_1768008163281",
    "lane": "rosette",
    "name": "Safe Default",
    "params": {
      "feed_xy": 800,
      "stepdown": 1.0
    },
    "created_at": 1768008163.2815561
  },
  {
    "id": "rosette_preset_1768008732912",
    "lane": "rosette",
    "name": "Safe Default",
    "params": {
      "feed_xy": 800,
      "stepdown": 1.0
    },
    "created_at": 1768008732.9127388
  },
  {
    "id": "rosette_preset_1768061566681",
    "lane": "rosette",
    "name": "Safe Default",
    "params": {
      "feed_xy": 800,
      "stepdown": 1.0
    },
    "created_at": 1768061566.68187
  },
  {
    "id": "rosette_preset_1768773311645",
    "lane": "rosette",
    "name": "Safe Default",
    "params": {
      "feed_xy": 800,
      "stepdown": 1.0
    },
    "created_at": 1768773311.645064
  },
  {
    "id": "rosette_preset_1769005882228",
    "lane": "rosette",
    "name": "Safe Default",
    "params": {
      "feed_xy": 800,
      "stepdown": 1.0
    },
    "created_at": 1769005882.2287023
  },
  {
    "id": "rosette_preset_1769808271579",
    "lane": "rosette",
    "name": "Safe Default",
    "params": {
      "feed_xy": 800,
      "stepdown": 1.0
    },
    "created_at": 1769808271.5792243
  },
  {
    "id": "rosette_preset_1769809348104",
    "lane": "rosette",
    "name": "Safe Default",
    "params": {
      "feed_xy": 800,
      "stepdown": 1.0
    },
    "created_at": 1769809348.1043072
  },
  {
    "id": "rosette_preset_1769810559191",
    "lane": "rosette",
    "name": "Safe Default",
    "params": {
      "feed_xy": 800,
      "stepdown": 1.0
    },
    "created_at": 1769810559.1914697
  },
  {
    "id": "rosette_preset_1769812086601",
    "lane": "rosette",
    "name": "Safe Default",
    "params": {
      "feed_xy": 800,
      "stepdown": 1.0
    },
    "created_at": 1769812086.601562
  },
  {
    "id": "rosette_preset_1769812793066",
    "lane": "rosette",
    "name": "Safe Default",
    "params": {
      "feed_xy": 800,
      "stepdown": 1.0
    },
    "created_at": 1769812793.0668523
  },
  {
    "id": "rosette_preset_1769814688033",
    "lane": "rosette",
    "name": "Safe Default",
    "params": {
      "feed_xy": 800,
      "stepdown": 1.0
    },
    "created_at": 1769814688.0335035
  },
  {
    "id": "rosette_preset_1769816648195",
    "lane": "rosette",
    "name": "Safe Default",
    "params": {
      "feed_xy": 800,
      "stepdown": 1.0
    },
    "created_at": 1769816648.1953938
  },
  {
    "id": "rosette_preset_1769820951245",
    "lane": "rosette",
    "name": "Safe Default",
    "params": {
      "feed_xy": 800,
      "stepdown": 1.0
    },
    "created_at": 1769820951.2452068
  },
  {
    "id": "rosette_preset_1769822140067",
    "lane": "rosette",
    "name": "Safe Default",
    "params": {
      "feed_xy": 800,
      "stepdown": 1.0
    },
    "created_at": 1769822140.06779
  },
  {
    "id": "rosette_preset_1769822578028",
    "lane": "rosette",
    "name": "Safe Default",
    "params": {
      "feed_xy": 800,
      "stepdown": 1.0
    },
    "created_at": 1769822578.0283592
  },
  {
    "id": "rosette_preset_1769827082646",
    "lane": "rosette",
    "name": "Safe Default",
    "params": {
      "feed_xy": 800,
      "stepdown": 1.0
    },
    "created_at": 1769827082.6469154
  },
  {
    "id": "rosette_preset_1769839757722",
    "lane": "rosette",
    "name": "Safe Default",
    "params": {
      "feed_xy": 800,
      "stepdown": 1.0
    },
    "created_at": 1769839757.7229898
  },
  {
    "id": "rosette_preset_1769841520365",
    "lane": "rosette",
    "name": "Safe Default",
    "params": {
      "feed_xy": 800,
      "stepdown": 1.0
    },
    "created_at": 1769841520.365371
  },
  {
    "id": "rosette_preset_1770333516430",
    "lane": "rosette",
    "name": "Safe Default",
    "params": {
      "feed_xy": 800,
      "stepdown": 1.0
    },
    "created_at": 1770333516.4305756
  },
  {
    "id": "rosette_preset_1770407181465",
    "lane": "rosette",
    "name": "Safe Default",
    "params": {
      "feed_xy": 800,
      "stepdown": 1.0
    },
    "created_at": 1770407181.4655802
  },
  {
    "id": "rosette_preset_1770410623528",
    "lane": "rosette",
    "name": "Safe Default",
    "params": {
      "feed_xy": 800,
      "stepdown": 1.0
    },
    "created_at": 1770410623.5283084
  },
  {
    "id": "rosette_preset_1770414854129",
    "lane": "rosette",
    "name": "Safe Default",
    "params": {
      "feed_xy": 800,
      "stepdown": 1.0
    },
    "created_at": 1770414854.1294305
  },
  {
    "id": "rosette_preset_1770415208750",
    "lane": "rosette",
    "name": "Safe Default",
    "params": {
      "feed_xy": 800,
      "stepdown": 1.0
    },
    "created_at": 1770415208.7502131
  },
  {
    "id": "rosette_preset_1770418084087",
    "lane": "rosette",
    "name": "Safe Default",
    "params": {
      "feed_xy": 800,
      "stepdown": 1.0
    },
    "created_at": 1770418084.0875337
  },
  {
    "id": "rosette_preset_1770422779780",
    "lane": "rosette",
    "name": "Safe Default",
    "params": {
      "feed_xy": 800,
      "stepdown": 1.0
    },
    "created_at": 1770422779.7804463
  },
  {
    "id": "rosette_preset_1770424192104",
    "lane": "rosette",
    "name": "Safe Default",
    "params": {
      "feed_xy": 800,
      "stepdown": 1.0
    },
    "created_at": 1770424192.104254
  },
  {
    "id": "rosette_preset_1770459943258",
    "lane": "rosette",
    "name": "Safe Default",
    "params": {
      "feed_xy": 800,
      "stepdown": 1.0
    },
    "created_at": 1770459943.2582467
  },
  {
    "id": "rosette_preset_1770612713119",
    "lane": "rosette",
    "name": "Safe Default",
    "params": {
      "feed_xy": 800,
      "stepdown": 1.0
    },
    "created_at": 1770612713.119684
  },
  {
    "id": "rosette_preset_1770613511744",
    "lane": "rosette",
    "name": "Safe Default",
    "params": {
      "feed_xy": 800,
      "stepdown": 1.0
    },
    "created_at": 1770613511.744805
  },
  {
    "id": "rosette_preset_1770614574440",
    "lane": "rosette",
    "name": "Safe Default",
    "params": {
      "feed_xy": 800,
      "stepdown": 1.0
    },
    "created_at": 1770614574.4407277
  },
  {
    "id": "rosette_preset_1770617853376",
    "lane": "rosette",
    "name": "Safe Default",
    "params": {
      "feed_xy": 800,
      "stepdown": 1.0
    },
    "created_at": 1770617853.37645
  },
  {
    "id": "rosette_preset_1770618190717",
    "lane": "rosette",
    "name": "Safe Default",
    "params": {
      "feed_xy": 800,
      "stepdown": 1.0
    },
    "created_at": 1770618190.7175832
  },
  {
    "id": "rosette_preset_1770619400391",
    "lane": "rosette",
    "name": "Safe Default",
    "params": {
      "feed_xy": 800,
      "stepdown": 1.0
    },
    "created_at": 1770619400.39104
  },
  {
    "id": "rosette_preset_1770622200105",
    "lane": "rosette",
    "name": "Safe Default",
    "params": {
      "feed_xy": 800,
      "stepdown": 1.0
    },
    "created_at": 1770622200.1056442
  },
  {
    "id": "rosette_preset_1770650014658",
    "lane": "rosette",
    "name": "Safe Default",
    "params": {
      "feed_xy": 800,
      "stepdown": 1.0
    },
    "created_at": 1770650014.6582286
  },
  {
    "id": "rosette_preset_1770650211360",
    "lane": "rosette",
    "name": "Safe Default",
    "params": {
      "feed_xy": 800,
      "stepdown": 1.0
    },
    "created_at": 1770650211.3602107
  },
  {
    "id": "rosette_preset_1770673760001",
    "lane": "rosette",
    "name": "Safe Default",
    "params": {
      "feed_xy": 800,
      "stepdown": 1.0
    },
    "created_at": 1770673760.0019991
  },
  {
    "id": "rosette_preset_1770707864882",
    "lane": "rosette",
    "name": "Safe Default",
    "params": {
      "feed_xy": 800,
      "stepdown": 1.0
    },
    "created_at": 1770707864.8822725
  },
  {
    "id": "rosette_preset_1770709256054",
    "lane": "rosette",
    "name": "Safe Default",
    "params": {
      "feed_xy": 800,
      "stepdown": 1.0
    },
    "created_at": 1770709256.0543482
  }
]