{
  "threshold": 15,
  "violation_count": 85,
  "violations": [
    {
      "file": "app/tests/test_e2e_workflow_integration.py",
      "function": "test_complete_workflow_chain",
      "complexity": 29,
      "line": 108,
      "letter": "M"
    },
    {
      "file": "app/ci/generate_debt_report.py",
      "function": "generate_report",
      "complexity": 28,
      "line": 74,
      "letter": "F"
    },
    {
      "file": "app/workflow/sessions/store.py",
      "function": "create",
      "complexity": 27,
      "line": 133,
      "letter": "M"
    },
    {
      "file": "app/rmos/runs_v2/batch_tree.py",
      "function": "resolve_batch_root",
      "complexity": 27,
      "line": 37,
      "letter": "F"
    },
    {
      "file": "app/saw_lab/executions_lookup_service.py",
      "function": "get_latest_execution_for_decision",
      "complexity": 26,
      "line": 43,
      "letter": "F"
    },
    {
      "file": "app/tests/test_art_studio_promotion_intent_export_contract.py",
      "function": "test_canonical_export_returns_strict_v1_shape_when_approved",
      "complexity": 26,
      "line": 118,
      "letter": "F"
    },
    {
      "file": "app/cam/feedtime_l3.py",
      "function": "jerk_aware_time",
      "complexity": 25,
      "line": 26,
      "letter": "F"
    },
    {
      "file": "app/saw_lab/toolpaths_lookup_service.py",
      "function": "get_latest_toolpaths_for_decision",
      "complexity": 25,
      "line": 46,
      "letter": "F"
    },
    {
      "file": "app/_experimental/analytics/advanced_analytics.py",
      "function": "_extract_metric_pairs",
      "complexity": 25,
      "line": 23,
      "letter": "M"
    },
    {
      "file": "app/workflow/sessions/store.py",
      "function": "patch",
      "complexity": 25,
      "line": 221,
      "letter": "M"
    },
    {
      "file": "app/cam/contour_reconstructor.py",
      "function": "reconstruct_contours_from_dxf",
      "complexity": 24,
      "line": 305,
      "letter": "F"
    },
    {
      "file": "app/ci/boundary_imports/parser.py",
      "function": "parse_imports_and_symbols",
      "complexity": 24,
      "line": 87,
      "letter": "F"
    },
    {
      "file": "app/ai/transport/vision_client.py",
      "function": "analyze",
      "complexity": 24,
      "line": 207,
      "letter": "M"
    },
    {
      "file": "app/tests/test_dxf_r12_roundtrip.py",
      "function": "test_dxf_r12_roundtrip_closed_and_open",
      "complexity": 23,
      "line": 24,
      "letter": "F"
    },
    {
      "file": "app/_experimental/analytics/material_analytics.py",
      "function": "get_dimensional_analysis",
      "complexity": 23,
      "line": 74,
      "letter": "M"
    },
    {
      "file": "app/rmos/runs_v2/batch_tree.py",
      "function": "list_batch_tree",
      "complexity": 23,
      "line": 99,
      "letter": "F"
    },
    {
      "file": "app/rmos/runs_v2/index_meta.py",
      "function": "validate_index_meta",
      "complexity": 23,
      "line": 126,
      "letter": "F"
    },
    {
      "file": "app/post_injection_dropin.py",
      "function": "PostInjectionMiddleware",
      "complexity": 22,
      "line": 124,
      "letter": "C"
    },
    {
      "file": "app/_experimental/analytics/pattern_analytics.py",
      "function": "get_geometry_metrics",
      "complexity": 22,
      "line": 123,
      "letter": "M"
    },
    {
      "file": "app/routers/blueprint_cam/extraction.py",
      "function": "extract_loops_from_dxf",
      "complexity": 22,
      "line": 17,
      "letter": "F"
    },
    {
      "file": "app/rmos/runs_v2/batch_dashboard.py",
      "function": "_group_key_from_kind",
      "complexity": 22,
      "line": 32,
      "letter": "F"
    },
    {
      "file": "app/post_injection_dropin.py",
      "function": "dispatch",
      "complexity": 21,
      "line": 132,
      "letter": "M"
    },
    {
      "file": "app/ltb_calculators/fraction_calculator_cli.py",
      "function": "calculator_repl",
      "complexity": 21,
      "line": 176,
      "letter": "F"
    },
    {
      "file": "app/rmos/runs_v2/batch_timeline.py",
      "function": "build_batch_timeline",
      "complexity": 21,
      "line": 70,
      "letter": "F"
    },
    {
      "file": "app/rmos/runs_v2/index_meta.py",
      "function": "normalize_index_meta",
      "complexity": 21,
      "line": 52,
      "letter": "F"
    },
    {
      "file": "app/rmos/run_artifacts/store.py",
      "function": "query_run_artifacts",
      "complexity": 21,
      "line": 78,
      "letter": "F"
    },
    {
      "file": "app/rmos/pipeline/feedback/learning.py",
      "function": "resolve_multipliers",
      "complexity": 21,
      "line": 312,
      "letter": "M"
    },
    {
      "file": "app/calculators/wiring/switch_validator.py",
      "function": "validate_switch_config",
      "complexity": 21,
      "line": 56,
      "letter": "F"
    },
    {
      "file": "app/art_studio/services/rosette_preview_renderer.py",
      "function": "render_rosette_preview_svg",
      "complexity": 21,
      "line": 27,
      "letter": "F"
    },
    {
      "file": "scripts/validate_endpoint_truth.py",
      "function": "main",
      "complexity": 20,
      "line": 18,
      "letter": "F"
    },
    {
      "file": "app/ai_context_adapter/routes.py",
      "function": "build_context",
      "complexity": 20,
      "line": 391,
      "letter": "F"
    },
    {
      "file": "app/cam/helical_core.py",
      "function": "helical_validate",
      "complexity": 20,
      "line": 199,
      "letter": "F"
    },
    {
      "file": "app/generators/lespaul_dxf_reader.py",
      "function": "_entity_to_points",
      "complexity": 20,
      "line": 69,
      "letter": "M"
    },
    {
      "file": "app/instrument_geometry/fan_fret_guard.py",
      "function": "compute_fan_fret_geometry_guard",
      "complexity": 20,
      "line": 31,
      "letter": "F"
    },
    {
      "file": "app/services/compare_risk_aggregate.py",
      "function": "aggregate_compare_history",
      "complexity": 20,
      "line": 28,
      "letter": "F"
    },
    {
      "file": "app/_experimental/ai_cam/explain_gcode.py",
      "function": "_explain_line",
      "complexity": 20,
      "line": 156,
      "letter": "M"
    },
    {
      "file": "app/rmos/runs_v2/api_runs_explain.py",
      "function": "explain_run_on_demand",
      "complexity": 20,
      "line": 23,
      "letter": "F"
    },
    {
      "file": "app/cam_core/saw_lab/saw_blade_registry.py",
      "function": "search",
      "complexity": 20,
      "line": 245,
      "letter": "M"
    },
    {
      "file": "app/art_studio/services/design_snapshot_store.py",
      "function": "list_recent",
      "complexity": 20,
      "line": 171,
      "letter": "M"
    },
    {
      "file": "app/services/saw_lab_toolpaths_from_decision_service.py",
      "function": "generate_toolpaths_from_decision",
      "complexity": 19,
      "line": 91,
      "letter": "F"
    },
    {
      "file": "app/tests/test_e2e_workflow_integration.py",
      "function": "TestEndToEndWorkflowIntegration",
      "complexity": 19,
      "line": 105,
      "letter": "C"
    },
    {
      "file": "app/_experimental/cnc_production/joblog/storage.py",
      "function": "compute_telemetry_stats",
      "complexity": 19,
      "line": 297,
      "letter": "F"
    },
    {
      "file": "app/tests/instrument_geometry/test_instrument_geometry_imports.py",
      "function": "test_instrument_geometry_public_api_imports",
      "complexity": 19,
      "line": 3,
      "letter": "F"
    },
    {
      "file": "app/rmos/posts/linuxcnc.py",
      "function": "validate_for_linuxcnc",
      "complexity": 19,
      "line": 147,
      "letter": "F"
    },
    {
      "file": "app/rmos/runs_v2/advisory_router.py",
      "function": "review_advisory_variant",
      "complexity": 19,
      "line": 123,
      "letter": "F"
    },
    {
      "file": "app/art_studio/services/pattern_store.py",
      "function": "list_patterns",
      "complexity": 19,
      "line": 163,
      "letter": "M"
    },
    {
      "file": "scripts/check_routing_truth.py",
      "function": "_validate_truth_shape",
      "complexity": 18,
      "line": 101,
      "letter": "F"
    },
    {
      "file": "scripts/saw_lab_enhance_blades_and_overrides.py",
      "function": "learn_overrides_from_samples",
      "complexity": 18,
      "line": 282,
      "letter": "F"
    },
    {
      "file": "app/cam/trochoid_l3.py",
      "function": "insert_trochoids",
      "complexity": 18,
      "line": 183,
      "letter": "F"
    },
    {
      "file": "app/saw_lab/executions_list_service.py",
      "function": "list_executions_for_decision",
      "complexity": 18,
      "line": 59,
      "letter": "F"
    },
    {
      "file": "app/routers/adaptive/helpers.py",
      "function": "_apply_adaptive_feed",
      "complexity": 18,
      "line": 96,
      "letter": "F"
    },
    {
      "file": "app/routers/geometry/import_router.py",
      "function": "parity",
      "complexity": 18,
      "line": 273,
      "letter": "F"
    },
    {
      "file": "app/rmos/posts/base.py",
      "function": "render_moves_base",
      "complexity": 18,
      "line": 229,
      "letter": "F"
    },
    {
      "file": "app/rmos/posts/grbl.py",
      "function": "validate_for_grbl",
      "complexity": 18,
      "line": 156,
      "letter": "F"
    },
    {
      "file": "app/rmos/runs_v2/advisory_router.py",
      "function": "bulk_review",
      "complexity": 18,
      "line": 205,
      "letter": "F"
    },
    {
      "file": "app/rmos/runs_v2/bind_art_studio_service.py",
      "function": "bind_art_studio_candidate",
      "complexity": 18,
      "line": 103,
      "letter": "F"
    },
    {
      "file": "app/rmos/runs_v2/db/store.py",
      "function": "list",
      "complexity": 18,
      "line": 140,
      "letter": "M"
    },
    {
      "file": "scripts/check_routing_truth.py",
      "function": "main",
      "complexity": 17,
      "line": 168,
      "letter": "F"
    },
    {
      "file": "tests/test_compare_risk_aggregate.py",
      "function": "test_aggregate_multiple_buckets",
      "complexity": 17,
      "line": 88,
      "letter": "F"
    },
    {
      "file": "tests/test_compare_risk_aggregate.py",
      "function": "test_aggregate_risk_labels",
      "complexity": 17,
      "line": 136,
      "letter": "F"
    },
    {
      "file": "app/advisory/store.py",
      "function": "list_assets",
      "complexity": 17,
      "line": 148,
      "letter": "M"
    },
    {
      "file": "app/ci/check_all_fences.py",
      "function": "main",
      "complexity": 17,
      "line": 47,
      "letter": "F"
    },
    {
      "file": "app/saw_lab/decision_intelligence_router.py",
      "function": "approve_suggestion",
      "complexity": 17,
      "line": 89,
      "letter": "F"
    },
    {
      "file": "app/services/geometry_diff.py",
      "function": "annotate_geometries_with_colors",
      "complexity": 17,
      "line": 65,
      "letter": "F"
    },
    {
      "file": "app/services/relief_kernels.py",
      "function": "plan_relief_finishing",
      "complexity": 17,
      "line": 245,
      "letter": "F"
    },
    {
      "file": "app/_experimental/ai_cam/optimize.py",
      "function": "_score_physics",
      "complexity": 17,
      "line": 163,
      "letter": "M"
    },
    {
      "file": "app/workflow/sessions/routes.py",
      "function": "workflow_advisory_summary",
      "complexity": 17,
      "line": 261,
      "letter": "F"
    },
    {
      "file": "app/routers/geometry/import_router.py",
      "function": "_svg_path_to_segments",
      "complexity": 17,
      "line": 54,
      "letter": "F"
    },
    {
      "file": "app/rmos/runs_v2/batch_timeline.py",
      "function": "get_batch_progress",
      "complexity": 17,
      "line": 177,
      "letter": "F"
    },
    {
      "file": "app/generators/lespaul_gcode/perimeter.py",
      "function": "generate_body_perimeter",
      "complexity": 17,
      "line": 29,
      "letter": "M"
    },
    {
      "file": "scripts/saw_lab_enhance_blades_and_overrides.py",
      "function": "_extract_training_samples_from_artifacts",
      "complexity": 16,
      "line": 210,
      "letter": "F"
    },
    {
      "file": "tests/test_runs_v2_delete_audit.py",
      "function": "test_hard_delete_removes_artifact_and_updates_index",
      "complexity": 16,
      "line": 82,
      "letter": "F"
    },
    {
      "file": "app/calculators/inlay_calc.py",
      "function": "calculate_fretboard_inlays",
      "complexity": 16,
      "line": 245,
      "letter": "F"
    },
    {
      "file": "app/cam/feedtime.py",
      "function": "estimate_time",
      "complexity": 16,
      "line": 114,
      "letter": "F"
    },
    {
      "file": "app/governance/endpoint_middleware.py",
      "function": "EndpointGovernanceMiddleware",
      "complexity": 16,
      "line": 50,
      "letter": "C"
    },
    {
      "file": "app/rmos/fret_cam_guard.py",
      "function": "run_fret_cam_guard",
      "complexity": 16,
      "line": 179,
      "letter": "F"
    },
    {
      "file": "app/rmos/moves.py",
      "function": "move_to_gcode",
      "complexity": 16,
      "line": 151,
      "letter": "F"
    },
    {
      "file": "app/saw_lab/execution_lifecycle_router.py",
      "function": "complete_execution",
      "complexity": 16,
      "line": 199,
      "letter": "F"
    },
    {
      "file": "app/saw_lab/execution_metrics_rollup_service.py",
      "function": "write_execution_metrics_rollup_artifact",
      "complexity": 16,
      "line": 112,
      "letter": "F"
    },
    {
      "file": "app/tests/test_art_studio_cam_promotion_contract.py",
      "function": "test_promote_succeeds_when_approved",
      "complexity": 16,
      "line": 86,
      "letter": "F"
    },
    {
      "file": "app/routers/geometry/import_router.py",
      "function": "import_geometry",
      "complexity": 16,
      "line": 204,
      "letter": "F"
    },
    {
      "file": "app/rmos/posts/fanuc.py",
      "function": "_render_moves",
      "complexity": 16,
      "line": 138,
      "letter": "F"
    },
    {
      "file": "app/rmos/runs_v2/api_runs_advisory.py",
      "function": "suggest_and_attach",
      "complexity": 16,
      "line": 140,
      "letter": "F"
    },
    {
      "file": "app/rmos/runs_v2/batch_dashboard.py",
      "function": "_try_extract_metrics_for_execution",
      "complexity": 16,
      "line": 118,
      "letter": "F"
    },
    {
      "file": "app/ai/transport/image_client.py",
      "function": "generate",
      "complexity": 16,
      "line": 291,
      "letter": "M"
    }
  ]
}